{"general": {"matchId": "3765831", "matchName": "Tunisia-vs-Oman_Fri, Dec 10, 2021, 15:00 UTC", "matchRound": "1/4", "teamColors": {"darkMode": {"home": "#D7393D", "away": "#ffffff"}, "lightMode": {"home": "#D7393D", "away": "#000000"}, "fontDarkMode": {"home": "rgba(255, 255, 255, 1.0)", "away": "rgba(29, 29, 29, 1.0)"}, "fontLightMode": {"home": "rgba(255, 255, 255, 1.0)", "away": "rgba(255, 255, 255, 1.0)"}}, "leagueId": 876012, "leagueName": "FIFA Arab Cup Final Stage", "leagueRoundName": "1/4", "parentLeagueId": 10242, "countryCode": "INT", "homeTeam": {"name": "Tunisia", "id": 6719}, "awayTeam": {"name": "Oman", "id": 5824}, "coverageLevel": "lower", "matchTimeUTC": "Fri, Dec 10, 2021, 15:00 UTC", "matchTimeUTCDate": "2021-12-10T15:00:00.000Z", "started": true, "finished": true}, "header": {"teams": [{"name": "Tunisia", "id": 6719, "score": 2, "imageUrl": "https://images.fotmob.com/image_resources/logo/teamlogo/6719_small.png", "pageUrl": "/teams/6719/overview/tunisia", "fifaRank": 29}, {"name": "Oman", "id": 5824, "score": 1, "imageUrl": "https://images.fotmob.com/image_resources/logo/teamlogo/5824_small.png", "pageUrl": "/teams/5824/overview/oman", "fifaRank": 78}], "status": {"utcTime": "2021-12-10T15:00:00.000Z", "numberOfHomeRedCards": 0, "numberOfAwayRedCards": 0, "halfs": {"firstHalfStarted": "10.12.2021 16:00:17", "firstHalfEnded": "10.12.2021 16:49:09", "secondHalfStarted": "10.12.2021 17:03:20", "secondHalfEnded": "10.12.2021 17:53:53", "firstExtraHalfStarted": "", "secondExtraHalfStarted": "", "gameEnded": "10.12.2021 17:54:11"}, "finished": true, "started": true, "cancelled": false, "awarded": false, "scoreStr": "2 - 1", "reason": {"short": "FT", "shortKey": "fulltime_short", "long": "Full-Time", "longKey": "finished"}, "whoLostOnPenalties": null, "whoLostOnAggregated": ""}, "events": {"homeTeamGoals": {"Jaziri": [{"reactKey": "857574116Goal713207undefinedtrue", "timeStr": 16, "type": "Goal", "time": 16, "overloadTime": null, "eventId": 8575741, "player": {"id": 713207, "name": "Seifeddine Jaziri", "profileUrl": "/players/713207/seifeddine-jaziri"}, "homeScore": 0, "awayScore": 0, "profileUrl": "/players/713207/seifeddine-jaziri", "overloadTimeStr": false, "isHome": true, "ownGoal": null, "goalDescription": null, "goalDescriptionKey": null, "suffix": null, "suffixKey": null, "isPenaltyShootoutEvent": false, "nameStr": "Seifeddine Jaziri", "firstName": "Seifeddine", "lastName": "Jaziri", "fullName": "Seifeddine Jaziri", "playerId": 713207, "newScore": [1, 0], "penShootoutScore": null, "shotmapEvent": null, "assistStr": null, "assistProfileUrl": null}], "Msakni": [{"reactKey": "857601869Goal192134undefinedtrue", "timeStr": 69, "type": "Goal", "time": 69, "overloadTime": null, "eventId": 8576018, "player": {"id": 192134, "name": "Youssef Msakni", "profileUrl": "/players/192134/youssef-msakni"}, "homeScore": 1, "awayScore": 1, "profileUrl": "/players/192134/youssef-msakni", "overloadTimeStr": false, "isHome": true, "ownGoal": null, "goalDescription": null, "goalDescriptionKey": null, "suffix": null, "suffixKey": null, "isPenaltyShootoutEvent": false, "nameStr": "Youssef Msakni", "firstName": "Youssef", "lastName": "Msakni", "fullName": "Youssef Msakni", "playerId": 192134, "newScore": [2, 1], "penShootoutScore": null, "shotmapEvent": null, "assistStr": null, "assistProfileUrl": null}]}, "awayTeamGoals": {"Al Alawi": [{"reactKey": "857601266Goal1101462undefinedfalse", "timeStr": 66, "type": "Goal", "time": 66, "overloadTime": null, "eventId": 8576012, "player": {"id": 1101462, "name": "Arshad Al Alawi", "profileUrl": "/players/1101462/arshad-al-alawi"}, "homeScore": 1, "awayScore": 0, "profileUrl": "/players/1101462/arshad-al-alawi", "overloadTimeStr": false, "isHome": false, "ownGoal": null, "goalDescription": null, "goalDescriptionKey": null, "suffix": null, "suffixKey": null, "isPenaltyShootoutEvent": false, "nameStr": "Arshad Al Alawi", "firstName": "Arshad", "lastName": "Al Alawi", "fullName": "Arshad Al Alawi", "playerId": 1101462, "newScore": [1, 1], "penShootoutScore": null, "shotmapEvent": null, "assistStr": null, "assistProfileUrl": null}]}, "homeTeamRedCards": {}, "awayTeamRedCards": {}}}, "nav": ["matchfacts", "head to head"], "ongoing": false, "hasPendingVAR": false, "content": {"matchFacts": {"matchId": 3765831, "highlights": null, "playerOfTheMatch": {}, "events": {"ongoing": false, "events": [{"reactKey": "857574116Goal713207undefinedtrue", "timeStr": 16, "type": "Goal", "time": 16, "overloadTime": null, "eventId": 8575741, "player": {"id": 713207, "name": "Seifeddine Jaziri", "profileUrl": "/players/713207/seifeddine-jaziri"}, "homeScore": 0, "awayScore": 0, "profileUrl": "/players/713207/seifeddine-jaziri", "overloadTimeStr": false, "isHome": true, "ownGoal": null, "goalDescription": null, "goalDescriptionKey": null, "suffix": null, "suffixKey": null, "isPenaltyShootoutEvent": false, "nameStr": "Seifeddine Jaziri", "firstName": "Seifeddine", "lastName": "Jaziri", "fullName": "Seifeddine Jaziri", "playerId": 713207, "newScore": [1, 0], "penShootoutScore": null, "shotmapEvent": null, "assistStr": null, "assistProfileUrl": null}, {"reactKey": "undefined45HalfNaNundefinedundefined", "timeStr": 45, "type": "Half", "time": 45, "overloadTime": null, "player": {"id": null, "profileUrl": ""}, "homeScore": 1, "awayScore": 0, "halfStrShort": "HT", "halfStrKey": "halftime_short"}, {"reactKey": "857601266Goal1101462undefinedfalse", "timeStr": 66, "type": "Goal", "time": 66, "overloadTime": null, "eventId": 8576012, "player": {"id": 1101462, "name": "Arshad Al Alawi", "profileUrl": "/players/1101462/arshad-al-alawi"}, "homeScore": 1, "awayScore": 0, "profileUrl": "/players/1101462/arshad-al-alawi", "overloadTimeStr": false, "isHome": false, "ownGoal": null, "goalDescription": null, "goalDescriptionKey": null, "suffix": null, "suffixKey": null, "isPenaltyShootoutEvent": false, "nameStr": "Arshad Al Alawi", "firstName": "Arshad", "lastName": "Al Alawi", "fullName": "Arshad Al Alawi", "playerId": 1101462, "newScore": [1, 1], "penShootoutScore": null, "shotmapEvent": null, "assistStr": null, "assistProfileUrl": null}, {"reactKey": "857601869Goal192134undefinedtrue", "timeStr": 69, "type": "Goal", "time": 69, "overloadTime": null, "eventId": 8576018, "player": {"id": 192134, "name": "Youssef Msakni", "profileUrl": "/players/192134/youssef-msakni"}, "homeScore": 1, "awayScore": 1, "profileUrl": "/players/192134/youssef-msakni", "overloadTimeStr": false, "isHome": true, "ownGoal": null, "goalDescription": null, "goalDescriptionKey": null, "suffix": null, "suffixKey": null, "isPenaltyShootoutEvent": false, "nameStr": "Youssef Msakni", "firstName": "Youssef", "lastName": "Msakni", "fullName": "Youssef Msakni", "playerId": 192134, "newScore": [2, 1], "penShootoutScore": null, "shotmapEvent": null, "assistStr": null, "assistProfileUrl": null}, {"reactKey": "undefined90HalfNaNundefinedundefined", "timeStr": 90, "type": "Half", "time": 90, "overloadTime": null, "player": {"id": null, "profileUrl": ""}, "homeScore": 2, "awayScore": 1, "halfStrShort": "FT", "halfStrKey": "fulltime_short"}], "eventTypes": ["Goal", "Half"], "penaltyShootoutEvents": null}, "infoBox": {"legInfo": null, "Match Date": {"utcTime": "2021-12-10T15:00:00.000Z", "isDateCorrect": true}, "Tournament": {"id": 876012, "parentLeagueId": 10242, "link": "/leagues/10242/overview/fifa-arab-cup-final-stage", "leagueName": "FIFA Arab Cup Final Stage", "roundName": "1/4", "round": "1/4"}, "Stadium": null, "Referee": {"text": "", "countryCode": "", "country": ""}, "Attendance": null}, "teamForm": [[{"result": -1, "resultString": "L", "imageUrl": "https://images.fotmob.com/image_resources/logo/teamlogo/8323_xsmall.png", "linkToMatch": "/matches/tunisia-vs-equatorial-guinea/1vd4km#3594960", "date": {"utcTime": "2021-11-13T16:00:00.000Z"}, "teamPageUrl": "/teams/8323/overview/equatorial-guinea", "tooltipText": {"utcTime": "2021-11-13T16:00:00.000Z", "homeTeam": "Equatorial Guinea", "homeTeamId": 8323, "homeScore": "1", "awayTeam": "Tunisia", "awayTeamId": 6719, "awayScore": "0"}, "score": "1 - 0", "home": {"id": "8323", "name": "Equatorial Guinea", "isOurTeam": false}, "away": {"id": "6719", "name": "Tunisia", "isOurTeam": true}}, {"result": 1, "resultString": "W", "imageUrl": "https://images.fotmob.com/image_resources/logo/teamlogo/6277_xsmall.png", "linkToMatch": "/matches/zambia-vs-tunisia/1eaap5#3594962", "date": {"utcTime": "2021-11-16T19:00:00.000Z"}, "teamPageUrl": "/teams/6277/overview/zambia", "tooltipText": {"utcTime": "2021-11-16T19:00:00.000Z", "homeTeam": "Tunisia", "homeTeamId": 6719, "homeScore": "3", "awayTeam": "Zambia", "awayTeamId": 6277, "awayScore": "1"}, "score": "3 - 1", "home": {"id": "6719", "name": "Tunisia", "isOurTeam": true}, "away": {"id": "6277", "name": "Zambia", "isOurTeam": false}}, {"result": 1, "resultString": "W", "imageUrl": "https://images.fotmob.com/image_resources/logo/teamlogo/68374_xsmall.png", "linkToMatch": "/matches/tunisia-vs-mauritania/1amphwd#3618563", "date": {"utcTime": "2021-11-30T10:00:00.000Z"}, "teamPageUrl": "/teams/68374/overview/mauritania", "tooltipText": {"utcTime": "2021-11-30T10:00:00.000Z", "homeTeam": "Tunisia", "homeTeamId": 6719, "homeScore": "5", "awayTeam": "Mauritania", "awayTeamId": 68374, "awayScore": "1"}, "score": "5 - 1", "home": {"id": "6719", "name": "Tunisia", "isOurTeam": true}, "away": {"id": "68374", "name": "Mauritania", "isOurTeam": false}}, {"result": -1, "resultString": "L", "imageUrl": "https://images.fotmob.com/image_resources/logo/teamlogo/6320_xsmall.png", "linkToMatch": "/matches/syria-vs-tunisia/1emamf#3614534", "date": {"utcTime": "2021-12-03T19:00:00.000Z"}, "teamPageUrl": "/teams/6320/overview/syria", "tooltipText": {"utcTime": "2021-12-03T19:00:00.000Z", "homeTeam": "Syria", "homeTeamId": 6320, "homeScore": "2", "awayTeam": "Tunisia", "awayTeamId": 6719, "awayScore": "0"}, "score": "2 - 0", "home": {"id": "6320", "name": "Syria", "isOurTeam": false}, "away": {"id": "6719", "name": "Tunisia", "isOurTeam": true}}, {"result": 1, "resultString": "W", "imageUrl": "https://images.fotmob.com/image_resources/logo/teamlogo/5789_xsmall.png", "linkToMatch": "/matches/uae-vs-tunisia/1akwtx#3614535", "date": {"utcTime": "2021-12-06T15:00:00.000Z"}, "teamPageUrl": "/teams/5789/overview/uae", "tooltipText": {"utcTime": "2021-12-06T15:00:00.000Z", "homeTeam": "Tunisia", "homeTeamId": 6719, "homeScore": "1", "awayTeam": "UAE", "awayTeamId": 5789, "awayScore": "0"}, "score": "1 - 0", "home": {"id": "6719", "name": "Tunisia", "isOurTeam": true}, "away": {"id": "5789", "name": "UAE", "isOurTeam": false}}], [{"result": 0, "resultString": "D", "imageUrl": "https://images.fotmob.com/image_resources/logo/teamlogo/5822_xsmall.png", "linkToMatch": "/matches/china-vs-oman/14dr41#3630935", "date": {"utcTime": "2021-11-11T15:00:00.000Z"}, "teamPageUrl": "/teams/5822/overview/china", "tooltipText": {"utcTime": "2021-11-11T15:00:00.000Z", "homeTeam": "China", "homeTeamId": 5822, "homeScore": "1", "awayTeam": "Oman", "awayTeamId": 5824, "awayScore": "1"}, "score": "1 - 1", "home": {"id": "5822", "name": "China", "isOurTeam": false}, "away": {"id": "5824", "name": "Oman", "isOurTeam": true}}, {"result": -1, "resultString": "L", "imageUrl": "https://images.fotmob.com/image_resources/logo/teamlogo/6715_xsmall.png", "linkToMatch": "/matches/oman-vs-japan/1at8ed#3630938", "date": {"utcTime": "2021-11-16T16:00:00.000Z"}, "teamPageUrl": "/teams/6715/overview/japan", "tooltipText": {"utcTime": "2021-11-16T16:00:00.000Z", "homeTeam": "Oman", "homeTeamId": 5824, "homeScore": "0", "awayTeam": "Japan", "awayTeamId": 6715, "awayScore": "1"}, "score": "0 - 1", "home": {"id": "5824", "name": "Oman", "isOurTeam": true}, "away": {"id": "6715", "name": "Japan", "isOurTeam": false}}, {"result": 0, "resultString": "D", "imageUrl": "https://images.fotmob.com/image_resources/logo/teamlogo/5819_xsmall.png", "linkToMatch": "/matches/iraq-vs-oman/14d05m#3615926", "date": {"utcTime": "2021-11-30T13:00:00.000Z"}, "teamPageUrl": "/teams/5819/overview/iraq", "tooltipText": {"utcTime": "2021-11-30T13:00:00.000Z", "homeTeam": "Iraq", "homeTeamId": 5819, "homeScore": "1", "awayTeam": "Oman", "awayTeamId": 5824, "awayScore": "1"}, "score": "1 - 1", "home": {"id": "5819", "name": "Iraq", "isOurTeam": false}, "away": {"id": "5824", "name": "Oman", "isOurTeam": true}}, {"result": -1, "resultString": "L", "imageUrl": "https://images.fotmob.com/image_resources/logo/teamlogo/5902_xsmall.png", "linkToMatch": "/matches/oman-vs-qatar/14xsk7#3615927", "date": {"utcTime": "2021-12-03T13:00:00.000Z"}, "teamPageUrl": "/teams/5902/overview/qatar", "tooltipText": {"utcTime": "2021-12-03T13:00:00.000Z", "homeTeam": "Oman", "homeTeamId": 5824, "homeScore": "1", "awayTeam": "Qatar", "awayTeamId": 5902, "awayScore": "2"}, "score": "1 - 2", "home": {"id": "5824", "name": "Oman", "isOurTeam": true}, "away": {"id": "5902", "name": "Qatar", "isOurTeam": false}}, {"result": 1, "resultString": "W", "imageUrl": "https://images.fotmob.com/image_resources/logo/teamlogo/5901_xsmall.png", "linkToMatch": "/matches/oman-vs-bahrain/14xjig#3625614", "date": {"utcTime": "2021-12-06T19:00:00.000Z"}, "teamPageUrl": "/teams/5901/overview/bahrain", "tooltipText": {"utcTime": "2021-12-06T19:00:00.000Z", "homeTeam": "Oman", "homeTeamId": 5824, "homeScore": "3", "awayTeam": "Bahrain", "awayTeamId": 5901, "awayScore": "0"}, "score": "3 - 0", "home": {"id": "5824", "name": "Oman", "isOurTeam": true}, "away": {"id": "5901", "name": "Bahrain", "isOurTeam": false}}]], "poll": {"oddspoll": {"PollName": "oddspoll-match-3765831", "MatchId": 3765831, "HomeTeamId": 6719, "AwayTeamId": 5824, "HomeTeam": "Tunisia", "AwayTeam": "Oman", "Facts": [{"OddsType": "1x2", "DefaultLabel": "Who will win?", "TextLabelId": "who_will_win", "DefaultTemplate": "{0} have {1}W, {2}D, {3}L in five matches while {4} have {5}W, {6}D, {7}L.", "TextTemplateId": "team_form_both", "StatValues": ["home_team", "3", "0", "2", "away_team", "1", "2", "2"], "DefaultLabels": ["1", "x", "2"], "LabelTemplates": ["label_1", "label_x", "label_2"], "Icon": "poll_teams", "defaultText": "Tunisia have 3W, 0D, 2L in five matches while Oman have 1W, 2D, 2L."}, {"OddsType": "bts", "DefaultLabel": "Will both teams score?", "TextLabelId": "both_score", "DefaultTemplate": "{0} have scored in their last {1} home matches.", "TextTemplateId": "goalstreak_team_home", "StatValues": ["home_team", "6"], "DefaultLabels": ["yes", "no"], "LabelTemplates": ["label_yes", "label_no"], "Icon": "poll_goal", "defaultText": "Tunisia have scored in their last 6 home matches."}, {"OddsType": "ou", "DefaultLabel": "Will there be more than 2.5 goals?", "TextLabelId": "over_under", "DefaultTemplate": "{0} have scored {3} goals in their last {2} matches, while {1} have scored {4}.", "TextTemplateId": "goals_total_last_3_both", "StatValues": ["home_team", "away_team", "3", "6", "5"], "DefaultLabels": ["yes", "no"], "LabelTemplates": ["label_yes", "label_no"], "Icon": "poll_goal", "defaultText": "Tunisia have scored 6 goals in their last 3 matches, while Oman have scored 5."}, {"OddsType": "dc", "DefaultLabel": "Double chance", "TextLabelId": "double_chance", "DefaultTemplate": "{0} haven't drawn in their last {1} matches.", "TextTemplateId": "draw_streak_team", "StatValues": ["home_team", "5"], "DefaultLabels": ["1x", "12", "x2"], "LabelTemplates": ["label_1x", "label_12", "label_x2"], "Icon": "poll_teams", "defaultText": "Tunisia haven't drawn in their last 5 matches."}]}, "renderToTop": false}, "topPlayers": {"homeTopPlayers": [], "awayTopPlayers": []}, "insights": [{"type": "team", "playerId": null, "teamId": 6719, "priority": 6, "defaultText": "Unbeaten in {0} home games", "localizedTextId": "insights_unbeaten_at_home", "statValues": [{"value": 6, "name": null, "type": "integer"}], "text": "Unbeaten in 6 home games", "color": "#D7393D"}], "countryCode": "INT", "QAData": [{"question": "Who won between Tunisia and Oman on Fri, 10 Dec 2021 15:00:00 GMT?", "answer": "Tunisia won 2\u20131 over Oman on Fri, 10 Dec 2021 15:00:00 GMT."}]}, "liveticker": false, "superlive": {"superLiveUrl": null, "showSuperLive": false}, "buzz": null, "stats": null, "playerStats": null, "shotmap": {"shots": [], "Periods": {"All": []}}, "lineup": null, "hasPlayoff": true, "table": false, "h2h": {"summary": [0, 0, 1], "matches": [{"time": {"utcTime": "2011-03-29T15:00:00.000Z"}, "matchUrl": "/matches/oman-vs-tunisia/1aub3z#969351", "league": {"name": "Friendlies", "id": "114", "pageUrl": "/leagues/114/overview/friendlies"}, "home": {"name": "Oman", "id": "5824"}, "status": {"utcTime": "2011-03-29T15:00:00.000Z", "finished": true, "started": true, "cancelled": false, "awarded": false, "scoreStr": "2 - 1", "reason": {"short": "FT", "shortKey": "fulltime_short", "long": "Full-Time", "longKey": "finished"}}, "finished": false, "away": {"name": "Tunisia", "id": "6719"}}]}, "momentum": false}, "seo": {"path": "tunisia-vs-oman", "eventJSONLD": {"@context": "https://schema.org", "@type": "SportsEvent", "sport": "Football/Soccer", "homeTeam": {"@context": "https://schema.org", "@type": "SportsTeam", "name": "Tunisia", "sport": "Football/Soccer", "logo": "https://images.fotmob.com/image_resources/logo/teamlogo/6719.png", "url": "https://www.fotmob.com/teams/6719/overview/tunisia", "location": null, "memberOf": null}, "awayTeam": {"@context": "https://schema.org", "@type": "SportsTeam", "name": "Oman", "sport": "Football/Soccer", "logo": "https://images.fotmob.com/image_resources/logo/teamlogo/5824.png", "url": "https://www.fotmob.com/teams/5824/overview/oman", "location": null, "memberOf": null}, "name": "Tunisia vs Oman", "description": "Follow Tunisia vs Oman live on fotmob.com", "startDate": "2021-12-10T15:00:00.000Z", "endDate": "2021-12-10T17:00:00.000Z", "eventStatus": "https://schema.org/EventScheduled", "eventAttendanceMode": "https://schema.org/OnlineEventAttendanceMode", "location": {"@type": "Place", "name": "Unknown stadium name", "address": {"@type": "PostalAddress", "addressCountry": "Unknown country", "addressLocality": "Unknown city"}}, "image": ["https://images.fotmob.com/image_resources/logo/teamlogo/6719.png", "https://images.fotmob.com/image_resources/logo/teamlogo/5824.png"], "organizer": {"@type": "Organization", "name": "FotMob", "url": "https://www.fotmob.com", "logo": "https://www.fotmob.com/img/fotmob_icon_2017.png"}, "offers": {"@type": "Offer", "url": "https://www.fotmob.com/match/3765831", "availability": "https://schema.org/InStock", "price": "0", "priceCurrency": "USD", "validFrom": "2021-12-10T15:00:00.000Z"}, "performer": [{"@type": "SportsTeam", "name": "Tunisia", "url": "https://www.fotmob.com/teams/6719/overview/tunisia"}, {"@type": "SportsTeam", "name": "Oman", "url": "https://www.fotmob.com/teams/5824/overview/oman"}]}, "breadcrumbJSONLD": [{"@context": "https://schema.org", "@type": "BreadcrumbList", "itemListElement": [{"@type": "ListItem", "position": 1, "name": "Home", "item": "https://www.fotmob.com"}, {"@type": "ListItem", "position": 2, "name": "FIFA Arab Cup Final Stage", "item": "https://www.fotmob.com/leagues/10242/overview/fifa-arab-cup-final-stage"}, {"@type": "ListItem", "position": 3, "name": "Tunisia - Oman", "item": "https://www.fotmob.com/match/3765831"}]}, {"@context": "https://schema.org", "@type": "BreadcrumbList", "itemListElement": [{"@type": "ListItem", "position": 1, "name": "Home", "item": "https://www.fotmob.com"}, {"@type": "ListItem", "position": 2, "name": "FIFA Arab Cup Final Stage", "item": "https://www.fotmob.com/leagues/10242/overview/fifa-arab-cup-final-stage"}, {"@type": "ListItem", "position": 3, "name": "Oman", "item": "https://www.fotmob.com/teams/5824/overview/oman"}, {"@type": "ListItem", "position": 4, "name": "Tunisia - Oman", "item": "https://www.fotmob.com/match/3765831"}]}, {"@context": "https://schema.org", "@type": "BreadcrumbList", "itemListElement": [{"@type": "ListItem", "position": 1, "name": "Home", "item": "https://www.fotmob.com"}, {"@type": "ListItem", "position": 2, "name": "FIFA Arab Cup Final Stage", "item": "https://www.fotmob.com/leagues/10242/overview/fifa-arab-cup-final-stage"}, {"@type": "ListItem", "position": 3, "name": "Tunisia", "item": "https://www.fotmob.com/teams/6719/overview/tunisia"}, {"@type": "ListItem", "position": 4, "name": "Tunisia - Oman", "item": "https://www.fotmob.com/match/3765831"}]}], "faqJSONLD": {"@context": "https://schema.org", "@type": "FAQPage", "mainEntity": [{"@type": "Question", "name": "Who won between Tunisia and Oman on Fri, 10 Dec 2021 15:00:00 GMT?", "acceptedAnswer": {"@type": "Answer", "text": "Tunisia won 2\u20131 over Oman on Fri, 10 Dec 2021 15:00:00 GMT."}}]}}}