{"general": {"matchId": "4058438", "matchName": "Albania-vs-Qatar_Wed, Nov 9, 2022, 17:30 UTC", "matchRound": null, "teamColors": {"darkMode": {"home": "#D82A2C", "away": "#983840"}, "lightMode": {"home": "#D82A2C", "away": "#983840"}, "fontDarkMode": {"home": "rgba(255, 255, 255, 1.0)", "away": "rgba(255, 255, 255, 1.0)"}, "fontLightMode": {"home": "rgba(255, 255, 255, 1.0)", "away": "rgba(255, 255, 255, 1.0)"}}, "leagueId": 877252, "leagueName": "Friendlies", "leagueRoundName": null, "parentLeagueId": 114, "countryCode": "INT", "homeTeam": {"name": "Albania", "id": 10024}, "awayTeam": {"name": "Qatar", "id": 5902}, "coverageLevel": "lower", "matchTimeUTC": "Wed, Nov 9, 2022, 17:30 UTC", "matchTimeUTCDate": "2022-11-09T17:30:00.000Z", "started": true, "finished": true}, "header": {"teams": [{"name": "Albania", "id": 10024, "score": 0, "imageUrl": "https://images.fotmob.com/image_resources/logo/teamlogo/10024_small.png", "pageUrl": "/teams/10024/overview/albania", "fifaRank": 66}, {"name": "Qatar", "id": 5902, "score": 1, "imageUrl": "https://images.fotmob.com/image_resources/logo/teamlogo/5902_small.png", "pageUrl": "/teams/5902/overview/qatar", "fifaRank": 50}], "status": {"utcTime": "2022-11-09T17:30:00.000Z", "numberOfHomeRedCards": 0, "numberOfAwayRedCards": 0, "halfs": {"firstHalfStarted": "09.11.2022 18:33:46", "firstHalfEnded": "09.11.2022 19:16:14", "secondHalfStarted": "09.11.2022 19:30:38", "secondHalfEnded": "09.11.2022 20:18:38", "firstExtraHalfStarted": "", "secondExtraHalfStarted": "", "gameEnded": "09.11.2022 20:18:38"}, "finished": true, "started": true, "cancelled": false, "awarded": false, "scoreStr": "0 - 1", "reason": {"short": "FT", "shortKey": "fulltime_short", "long": "Full-Time", "longKey": "finished"}, "whoLostOnPenalties": null, "whoLostOnAggregated": ""}, "events": {"homeTeamGoals": {}, "awayTeamGoals": {"Ali": [{"reactKey": "958102637Goal644017undefinedfalse", "timeStr": 37, "type": "Goal", "time": 37, "overloadTime": null, "eventId": 9581026, "player": {"id": 644017, "name": "Almoez Ali", "profileUrl": "/players/644017/almoez-ali"}, "homeScore": 0, "awayScore": 0, "profileUrl": "/players/644017/almoez-ali", "overloadTimeStr": false, "isHome": false, "ownGoal": null, "goalDescription": "Penalty", "goalDescriptionKey": "penalty", "suffix": "Pen", "suffixKey": "penalties_short", "isPenaltyShootoutEvent": false, "nameStr": "Almoez Ali", "firstName": "Almoez", "lastName": "Ali", "fullName": "Almoez Ali", "playerId": 644017, "newScore": [0, 1], "penShootoutScore": null, "shotmapEvent": null, "assistStr": null, "assistProfileUrl": null}]}, "homeTeamRedCards": {}, "awayTeamRedCards": {}}}, "nav": ["matchfacts", "lineup", "head to head"], "ongoing": false, "hasPendingVAR": false, "content": {"matchFacts": {"matchId": 4058438, "highlights": null, "playerOfTheMatch": {}, "events": {"ongoing": false, "events": [{"reactKey": "undefined26SubstitutionNaN431151false", "timeStr": 26, "type": "Substitution", "time": 26, "overloadTime": 0, "player": {"id": null, "profileUrl": ""}, "homeScore": 0, "awayScore": 0, "profileUrl": "", "overloadTimeStr": false, "isHome": false, "injuredPlayerOut": false, "swap": [{"name": "Mohammed Muntari", "id": "431151", "profileUrl": "/players/431151/mohammed-muntari"}, {"name": "Ahmed Alaaeldin", "id": "264096", "profileUrl": "/players/264096/ahmed-alaaeldin"}]}, {"reactKey": "958106036Card948468undefinedtrue", "timeStr": 36, "type": "Card", "time": 36, "overloadTime": null, "eventId": 9581060, "player": {"id": 948468, "name": "Stivian Janku", "profileUrl": "/players/948468/stivian-janku"}, "homeScore": 0, "awayScore": 0, "profileUrl": "/players/948468/stivian-janku", "overloadTimeStr": false, "isHome": true, "nameStr": "Stivian Janku", "firstName": "Stivian", "lastName": "Janku", "fullName": "Stivian Janku", "playerId": 948468, "card": "Yellow", "cardDescription": null}, {"reactKey": "958102637Goal644017undefinedfalse", "timeStr": 37, "type": "Goal", "time": 37, "overloadTime": null, "eventId": 9581026, "player": {"id": 644017, "name": "Almoez Ali", "profileUrl": "/players/644017/almoez-ali"}, "homeScore": 0, "awayScore": 0, "profileUrl": "/players/644017/almoez-ali", "overloadTimeStr": false, "isHome": false, "ownGoal": null, "goalDescription": "Penalty", "goalDescriptionKey": "penalty", "suffix": "Pen", "suffixKey": "penalties_short", "isPenaltyShootoutEvent": false, "nameStr": "Almoez Ali", "firstName": "Almoez", "lastName": "Ali", "fullName": "Almoez Ali", "playerId": 644017, "newScore": [0, 1], "penShootoutScore": null, "shotmapEvent": null, "assistStr": null, "assistProfileUrl": null}, {"reactKey": "undefined45HalfNaNundefinedundefined", "timeStr": 45, "type": "Half", "time": 45, "overloadTime": null, "player": {"id": null, "profileUrl": ""}, "homeScore": 0, "awayScore": 1, "halfStrShort": "HT", "halfStrKey": "halftime_short"}, {"reactKey": "undefined46SubstitutionNaN1178779true", "timeStr": 46, "type": "Substitution", "time": 46, "overloadTime": 0, "player": {"id": null, "profileUrl": ""}, "homeScore": 0, "awayScore": 1, "profileUrl": "", "overloadTimeStr": false, "isHome": true, "injuredPlayerOut": false, "swap": [{"name": "Alen Sherri", "id": "1178779", "profileUrl": "/players/1178779/alen-sherri"}, {"name": "Mario Dajsinani", "id": "761795", "profileUrl": "/players/761795/mario-dajsinani"}]}, {"reactKey": "undefined46SubstitutionNaN948198true", "timeStr": 46, "type": "Substitution", "time": 46, "overloadTime": 0, "player": {"id": null, "profileUrl": ""}, "homeScore": 0, "awayScore": 1, "profileUrl": "", "overloadTimeStr": false, "isHome": true, "injuredPlayerOut": false, "swap": [{"name": "Eneo Bitri", "id": "948198", "profileUrl": "/players/948198/eneo-bitri"}, {"name": "Stivian Janku", "id": "948468", "profileUrl": "/players/948468/stivian-janku"}]}, {"reactKey": "undefined46SubstitutionNaN1173758true", "timeStr": 46, "type": "Substitution", "time": 46, "overloadTime": 0, "player": {"id": null, "profileUrl": ""}, "homeScore": 0, "awayScore": 1, "profileUrl": "", "overloadTimeStr": false, "isHome": true, "injuredPlayerOut": false, "swap": [{"name": "Herald Marku", "id": "1173758", "profileUrl": "/players/1173758/herald-marku"}, {"name": "Sherif Kallaku", "id": "1067060", "profileUrl": "/players/1067060/sherif-kallaku"}]}, {"reactKey": "958141760Card1067465undefinedtrue", "timeStr": 60, "type": "Card", "time": 60, "overloadTime": null, "eventId": 9581417, "player": {"id": 1067465, "name": "Rudolf Turkaj", "profileUrl": "/players/1067465/rudolf-turkaj"}, "homeScore": 0, "awayScore": 1, "profileUrl": "/players/1067465/rudolf-turkaj", "overloadTimeStr": false, "isHome": true, "nameStr": "Rudolf Turkaj", "firstName": "Rudolf", "lastName": "Turkaj", "fullName": "Rudolf Turkaj", "playerId": 1067465, "card": "Yellow", "cardDescription": null}, {"reactKey": "undefined61SubstitutionNaN1009249false", "timeStr": 61, "type": "Substitution", "time": 61, "overloadTime": 0, "player": {"id": null, "profileUrl": ""}, "homeScore": 0, "awayScore": 1, "profileUrl": "", "overloadTimeStr": false, "isHome": false, "injuredPlayerOut": false, "swap": [{"name": "Mohammed Waad", "id": "1009249", "profileUrl": "/players/1009249/mohammed-waad"}, {"name": "Abdulaziz Hatem", "id": "308909", "profileUrl": "/players/308909/abdulaziz-hatem"}]}, {"reactKey": "undefined61SubstitutionNaN524007false", "timeStr": 61, "type": "Substitution", "time": 61, "overloadTime": 0, "player": {"id": null, "profileUrl": ""}, "homeScore": 0, "awayScore": 1, "profileUrl": "", "overloadTimeStr": false, "isHome": false, "injuredPlayerOut": false, "swap": [{"name": "Musab Kheder", "id": "524007", "profileUrl": "/players/524007/musab-kheder"}, {"name": "Homam Elamin", "id": "937414", "profileUrl": "/players/937414/homam-elamin"}]}, {"reactKey": "undefined64SubstitutionNaN1169358true", "timeStr": 64, "type": "Substitution", "time": 64, "overloadTime": 0, "player": {"id": null, "profileUrl": ""}, "homeScore": 0, "awayScore": 1, "profileUrl": "", "overloadTimeStr": false, "isHome": true, "injuredPlayerOut": false, "swap": [{"name": "Marsel Ismajlgeci", "id": "1169358", "profileUrl": "/players/1169358/marsel-ismajlgeci"}, {"name": "Esin Hakaj", "id": "762023", "profileUrl": "/players/762023/esin-hakaj"}]}, {"reactKey": "958145764Card251923undefinedfalse", "timeStr": 64, "type": "Card", "time": 64, "overloadTime": null, "eventId": 9581457, "player": {"id": 251923, "name": "Abdelkarim Hasan Fadlalla", "profileUrl": "/players/251923/abdelkarim-hasan-fadlalla"}, "homeScore": 0, "awayScore": 1, "profileUrl": "/players/251923/abdelkarim-hasan-fadlalla", "overloadTimeStr": false, "isHome": false, "nameStr": "Abdelkarim Hasan Fadlalla", "firstName": "Abdelkarim Hasan", "lastName": "Fadlalla", "fullName": "Abdelkarim Hasan Fadlalla", "playerId": 251923, "card": "Yellow", "cardDescription": null}, {"reactKey": "undefined65SubstitutionNaN1306240true", "timeStr": 65, "type": "Substitution", "time": 65, "overloadTime": 0, "player": {"id": null, "profileUrl": ""}, "homeScore": 0, "awayScore": 1, "profileUrl": "", "overloadTimeStr": false, "isHome": true, "injuredPlayerOut": false, "swap": [{"name": "Xhuliano Skuka", "id": "1306240", "profileUrl": "/players/1306240/xhuliano-skuka"}, {"name": "Tedi Cara", "id": "1159654", "profileUrl": "/players/1159654/tedi-cara"}]}, {"reactKey": "undefined75SubstitutionNaN309173false", "timeStr": 75, "type": "Substitution", "time": 75, "overloadTime": 0, "player": {"id": null, "profileUrl": ""}, "homeScore": 0, "awayScore": 1, "profileUrl": "", "overloadTimeStr": false, "isHome": false, "injuredPlayerOut": false, "swap": [{"name": "Ismael Mohammad", "id": "309173", "profileUrl": "/players/309173/ismael-mohammad"}, {"name": "Pedro Miguel", "id": "734637", "profileUrl": "/players/734637/pedro-miguel"}]}, {"reactKey": "undefined75SubstitutionNaN613792false", "timeStr": 75, "type": "Substitution", "time": 75, "overloadTime": 0, "player": {"id": null, "profileUrl": ""}, "homeScore": 0, "awayScore": 1, "profileUrl": "", "overloadTimeStr": false, "isHome": false, "injuredPlayerOut": false, "swap": [{"name": "Akram Afif", "id": "613792", "profileUrl": "/players/613792/akram-afif"}, {"name": "Almoez Ali", "id": "644017", "profileUrl": "/players/644017/almoez-ali"}]}, {"reactKey": "undefined75SubstitutionNaN615414false", "timeStr": 75, "type": "Substitution", "time": 75, "overloadTime": 0, "player": {"id": null, "profileUrl": ""}, "homeScore": 0, "awayScore": 1, "profileUrl": "", "overloadTimeStr": false, "isHome": false, "injuredPlayerOut": false, "swap": [{"name": "Assim Madibo", "id": "615414", "profileUrl": "/players/615414/assim-madibo"}, {"name": "Karim Boudiaf", "id": "309153", "profileUrl": "/players/309153/karim-boudiaf"}]}, {"reactKey": "undefined81SubstitutionNaN948251true", "timeStr": 81, "type": "Substitution", "time": 81, "overloadTime": 0, "player": {"id": null, "profileUrl": ""}, "homeScore": 0, "awayScore": 1, "profileUrl": "", "overloadTimeStr": false, "isHome": true, "injuredPlayerOut": false, "swap": [{"name": "Redon Xhixha", "id": "948251", "profileUrl": "/players/948251/redon-xhixha"}, {"name": "Kristal Abazaj", "id": "855297", "profileUrl": "/players/855297/kristal-abazaj"}]}, {"reactKey": "958174282Card309173undefinedfalse", "timeStr": 82, "type": "Card", "time": 82, "overloadTime": null, "eventId": 9581742, "player": {"id": 309173, "name": "Ismael Mohammad", "profileUrl": "/players/309173/ismael-mohammad"}, "homeScore": 0, "awayScore": 1, "profileUrl": "/players/309173/ismael-mohammad", "overloadTimeStr": false, "isHome": false, "nameStr": "Ismael Mohammad", "firstName": "Ismael", "lastName": "Mohammad", "fullName": "Ismael Mohammad", "playerId": 309173, "card": "Yellow", "cardDescription": null}, {"reactKey": "958182689Card948198undefinedtrue", "timeStr": 89, "type": "Card", "time": 89, "overloadTime": null, "eventId": 9581826, "player": {"id": 948198, "name": "Eneo Bitri", "profileUrl": "/players/948198/eneo-bitri"}, "homeScore": 0, "awayScore": 1, "profileUrl": "/players/948198/eneo-bitri", "overloadTimeStr": false, "isHome": true, "nameStr": "Eneo Bitri", "firstName": "Eneo", "lastName": "Bitri", "fullName": "Eneo Bitri", "playerId": 948198, "card": "Yellow", "cardDescription": null}, {"reactKey": "undefined90HalfNaNundefinedundefined", "timeStr": 90, "type": "Half", "time": 90, "overloadTime": null, "player": {"id": null, "profileUrl": ""}, "homeScore": 0, "awayScore": 1, "halfStrShort": "FT", "halfStrKey": "fulltime_short"}], "eventTypes": ["Substitution", "Card", "Goal", "Half", "Yellow"], "penaltyShootoutEvents": null}, "infoBox": {"legInfo": null, "Match Date": {"utcTime": "2022-11-09T17:30:00.000Z", "isDateCorrect": true}, "Tournament": {"id": 877252, "parentLeagueId": 114, "link": "/leagues/114/overview/friendlies", "leagueName": "Friendlies", "roundName": null, "round": null}, "Stadium": null, "Referee": {"text": "", "countryCode": "", "country": ""}, "Attendance": null}, "teamForm": [[{"result": 0, "resultString": "D", "imageUrl": "https://images.fotmob.com/image_resources/logo/teamlogo/8536_xsmall.png", "linkToMatch": "/matches/iceland-vs-albania/2uk0ig#3784566", "date": {"utcTime": "2022-06-06T18:45:00.000Z"}, "teamPageUrl": "/teams/8536/overview/iceland", "tooltipText": {"utcTime": "2022-06-06T18:45:00.000Z", "homeTeam": "Iceland", "homeTeamId": 8536, "homeScore": "1", "awayTeam": "Albania", "awayTeamId": 10024, "awayScore": "1"}, "score": "1 - 1", "home": {"id": "8536", "name": "Iceland", "isOurTeam": false}, "away": {"id": "10024", "name": "Albania", "isOurTeam": true}}, {"result": -1, "resultString": "L", "imageUrl": "https://images.fotmob.com/image_resources/logo/teamlogo/8567_xsmall.png", "linkToMatch": "/matches/israel-vs-albania/2uwcvb#3784568", "date": {"utcTime": "2022-06-10T18:50:00.000Z"}, "teamPageUrl": "/teams/8567/overview/israel", "tooltipText": {"utcTime": "2022-06-10T18:50:00.000Z", "homeTeam": "Albania", "homeTeamId": 10024, "homeScore": "1", "awayTeam": "Israel", "awayTeamId": 8567, "awayScore": "2"}, "score": "1 - 2", "home": {"id": "10024", "name": "Albania", "isOurTeam": true}, "away": {"id": "8567", "name": "Israel", "isOurTeam": false}}, {"result": 0, "resultString": "D", "imageUrl": "https://images.fotmob.com/image_resources/logo/teamlogo/8261_xsmall.png", "linkToMatch": "/matches/estonia-vs-albania/2rjf3k#3882256", "date": {"utcTime": "2022-06-13T16:00:00.000Z"}, "teamPageUrl": "/teams/8261/overview/estonia", "tooltipText": {"utcTime": "2022-06-13T16:00:00.000Z", "homeTeam": "Albania", "homeTeamId": 10024, "homeScore": "0", "awayTeam": "Estonia", "awayTeamId": 8261, "awayScore": "0"}, "score": "0 - 0", "home": {"id": "10024", "name": "Albania", "isOurTeam": true}, "away": {"id": "8261", "name": "Estonia", "isOurTeam": false}}, {"result": -1, "resultString": "L", "imageUrl": "https://images.fotmob.com/image_resources/logo/teamlogo/8567_xsmall.png", "linkToMatch": "/matches/israel-vs-albania/2uwcvb#3784573", "date": {"utcTime": "2022-09-24T18:45:00.000Z"}, "teamPageUrl": "/teams/8567/overview/israel", "tooltipText": {"utcTime": "2022-09-24T18:45:00.000Z", "homeTeam": "Israel", "homeTeamId": 8567, "homeScore": "2", "awayTeam": "Albania", "awayTeamId": 10024, "awayScore": "1"}, "score": "2 - 1", "home": {"id": "8567", "name": "Israel", "isOurTeam": false}, "away": {"id": "10024", "name": "Albania", "isOurTeam": true}}, {"result": 0, "resultString": "D", "imageUrl": "https://images.fotmob.com/image_resources/logo/teamlogo/8536_xsmall.png", "linkToMatch": "/matches/iceland-vs-albania/2uk0ig#3784574", "date": {"utcTime": "2022-09-27T18:45:00.000Z"}, "teamPageUrl": "/teams/8536/overview/iceland", "tooltipText": {"utcTime": "2022-09-27T18:45:00.000Z", "homeTeam": "Albania", "homeTeamId": 10024, "homeScore": "1", "awayTeam": "Iceland", "awayTeamId": 8536, "awayScore": "1"}, "score": "1 - 1", "home": {"id": "10024", "name": "Albania", "isOurTeam": true}, "away": {"id": "8536", "name": "Iceland", "isOurTeam": false}}], [{"result": -1, "resultString": "L", "imageUrl": "https://images.fotmob.com/image_resources/logo/teamlogo/5810_xsmall.png", "linkToMatch": "/matches/canada-vs-qatar/14u9ym#4025384", "date": {"utcTime": "2022-09-23T17:00:00.000Z"}, "teamPageUrl": "/teams/5810/overview/canada", "tooltipText": {"utcTime": "2022-09-23T17:00:00.000Z", "homeTeam": "Qatar", "homeTeamId": 5902, "homeScore": "0", "awayTeam": "Canada", "awayTeamId": 5810, "awayScore": "2"}, "score": "0 - 2", "home": {"id": "5902", "name": "Qatar", "isOurTeam": true}, "away": {"id": "5810", "name": "Canada", "isOurTeam": false}}, {"result": 0, "resultString": "D", "imageUrl": "https://images.fotmob.com/image_resources/logo/teamlogo/9762_xsmall.png", "linkToMatch": "/matches/qatar-vs-chile/211uey#4025385", "date": {"utcTime": "2022-09-27T17:00:00.000Z"}, "teamPageUrl": "/teams/9762/overview/chile", "tooltipText": {"utcTime": "2022-09-27T17:00:00.000Z", "homeTeam": "Qatar", "homeTeamId": 5902, "homeScore": "2", "awayTeam": "Chile", "awayTeamId": 9762, "awayScore": "2"}, "score": "2 - 2", "home": {"id": "5902", "name": "Qatar", "isOurTeam": true}, "away": {"id": "9762", "name": "Chile", "isOurTeam": false}}, {"result": 1, "resultString": "W", "imageUrl": "https://images.fotmob.com/image_resources/logo/teamlogo/5858_xsmall.png", "linkToMatch": "/matches/guatemala-vs-qatar/156cna#4044366", "date": {"utcTime": "2022-10-23T16:40:00.000Z"}, "teamPageUrl": "/teams/5858/overview/guatemala", "tooltipText": {"utcTime": "2022-10-23T16:40:00.000Z", "homeTeam": "Qatar", "homeTeamId": 5902, "homeScore": "2", "awayTeam": "Guatemala", "awayTeamId": 5858, "awayScore": "0"}, "score": "2 - 0", "home": {"id": "5902", "name": "Qatar", "isOurTeam": true}, "away": {"id": "5858", "name": "Guatemala", "isOurTeam": false}}, {"result": 1, "resultString": "W", "imageUrl": "https://images.fotmob.com/image_resources/logo/teamlogo/5808_xsmall.png", "linkToMatch": "/matches/honduras-vs-qatar/14trvz#4048894", "date": {"utcTime": "2022-10-27T16:35:00.000Z"}, "teamPageUrl": "/teams/5808/overview/honduras", "tooltipText": {"utcTime": "2022-10-27T16:35:00.000Z", "homeTeam": "Qatar", "homeTeamId": 5902, "homeScore": "1", "awayTeam": "Honduras", "awayTeamId": 5808, "awayScore": "0"}, "score": "1 - 0", "home": {"id": "5902", "name": "Qatar", "isOurTeam": true}, "away": {"id": "5808", "name": "Honduras", "isOurTeam": false}}, {"result": 1, "resultString": "W", "imageUrl": "https://images.fotmob.com/image_resources/logo/teamlogo/5922_xsmall.png", "linkToMatch": "/matches/qatar-vs-panama/15mj0a#4051981", "date": {"utcTime": "2022-11-05T17:30:00.000Z"}, "teamPageUrl": "/teams/5922/overview/panama", "tooltipText": {"utcTime": "2022-11-05T17:30:00.000Z", "homeTeam": "Qatar", "homeTeamId": 5902, "homeScore": "2", "awayTeam": "Panama", "awayTeamId": 5922, "awayScore": "1"}, "score": "2 - 1", "home": {"id": "5902", "name": "Qatar", "isOurTeam": true}, "away": {"id": "5922", "name": "Panama", "isOurTeam": false}}]], "poll": {"oddspoll": {"PollName": "oddspoll-match-4058438", "MatchId": 4058438, "HomeTeamId": 10024, "AwayTeamId": 5902, "HomeTeam": "Albania", "AwayTeam": "Qatar", "Facts": [{"OddsType": "1x2", "DefaultLabel": "Who will win?", "TextLabelId": "who_will_win", "DefaultTemplate": "{0} haven't lost in {1} matches.", "TextTemplateId": "undefeated_team", "StatValues": ["away_team", "4"], "DefaultLabels": ["1", "x", "2"], "LabelTemplates": ["label_1", "label_x", "label_2"], "Icon": "poll_stat_up", "defaultText": "Qatar haven't lost in 4 matches."}, {"OddsType": "bts", "DefaultLabel": "Will both teams score?", "TextLabelId": "both_score", "DefaultTemplate": "{0} have an average of {2} goals in their last three matches and {1} have an average of {3}.", "TextTemplateId": "average_goals_last3_both", "StatValues": ["home_team", "away_team", "0.67", "1.67"], "DefaultLabels": ["yes", "no"], "LabelTemplates": ["label_yes", "label_no"], "Icon": "poll_goal", "defaultText": "Albania have an average of 0.67 goals in their last three matches and Qatar have an average of 1.67."}, {"OddsType": "ou", "DefaultLabel": "Will there be more than 2.5 goals?", "TextLabelId": "over_under", "DefaultTemplate": "{0} have an average of {2} goals in their last three matches and {1} have an average of {3}.", "TextTemplateId": "average_goals_last3_both", "StatValues": ["home_team", "away_team", "0.67", "1.67"], "DefaultLabels": ["yes", "no"], "LabelTemplates": ["label_yes", "label_no"], "Icon": "poll_goal", "defaultText": "Albania have an average of 0.67 goals in their last three matches and Qatar have an average of 1.67."}, {"OddsType": "dc", "DefaultLabel": "Double chance", "TextLabelId": "double_chance", "DefaultTemplate": "{0} haven't won a match in {1} attempts.", "TextTemplateId": "not_won_team", "StatValues": ["home_team", "7"], "DefaultLabels": ["1x", "12", "x2"], "LabelTemplates": ["label_1x", "label_12", "label_x2"], "Icon": "poll_stat_down", "defaultText": "Albania haven't won a match in 7 attempts."}]}, "renderToTop": false}, "topPlayers": {"homeTopPlayers": [], "awayTopPlayers": []}, "insights": [{"type": "team", "playerId": null, "teamId": 10024, "priority": 1344, "defaultText": "Haven't won at home in their last {0} matches", "localizedTextId": "insights_not_won_at_home", "statValues": [{"value": 4, "name": null, "type": "integer"}], "text": "Haven't won at home in their last 4 matches", "color": "#D82A2C"}, {"type": "team", "playerId": null, "teamId": 10024, "priority": 8, "defaultText": "Haven't won a match in {0} attempts", "localizedTextId": "insights_not_won_team", "statValues": [{"value": 7, "name": null, "type": "integer"}], "text": "Haven't won a match in 7 attempts", "color": "#D82A2C"}], "topScorers": {"section": "Top scorers", "sectionId": 6, "homePlayer": {"playerId": 948247, "position": 3, "matchesWithRating": 1, "lastName": "Uzuni", "fullName": "Myrto Uzuni", "stats": {"goals": 1, "goalAssist": 0, "ontargetScoringAtt": 1, "motm": 0, "gamesPlayed": 2, "minsPlayed": 74, "minsPlayedGoal": 74, "playerRating": 6.87}}, "awayPlayer": {"playerId": 613792, "position": 3, "matchesWithRating": 5, "lastName": "Afif", "fullName": "Akram Afif", "stats": {"goals": 2, "goalAssist": 1, "ontargetScoringAtt": 1.5, "motm": 2, "gamesPlayed": 5, "minsPlayed": 450, "minsPlayedGoal": 225, "playerRating": 7.64}}, "statsOrder": ["playerRating", "goals", "goalAssist", "minsPlayedGoal", "ontargetScoringAtt", "motm", "gamesPlayed", "minsPlayed"]}, "countryCode": "INT", "QAData": [{"question": "Who won between Albania and Qatar on Wed, 09 Nov 2022 17:30:00 GMT?", "answer": "Qatar won 1\u20130 over Albania on Wed, 09 Nov 2022 17:30:00 GMT."}]}, "liveticker": false, "superlive": {"superLiveUrl": null, "showSuperLive": false}, "buzz": null, "stats": null, "playerStats": null, "shotmap": {"shots": [], "Periods": {"All": []}}, "lineup": {"matchId": 4058438, "lineupType": "standard", "availableFilters": ["match"], "homeTeam": {"id": 10024, "name": "Albania", "formation": "5-3-2", "starters": [{"id": 761795, "name": "Mario Dajsinani", "positionId": 11, "usualPlayingPositionId": 0, "shirtNumber": "1", "isCaptain": false, "horizontalLayout": {"x": 0.1, "y": 0.5, "height": 0.195, "width": 0.2}, "verticalLayout": {"x": 0.5, "y": 0.1, "height": 0.2, "width": 1}, "performance": {"events": [], "substitutionEvents": [{"time": 46, "type": "subOut", "reason": "tactical"}], "playerOfTheMatch": false}, "firstName": "Mario", "lastName": "Dajsinani", "rankings": null}, {"id": 1134051, "name": "Erdenis Gurishta", "positionId": 31, "usualPlayingPositionId": 1, "shirtNumber": "2", "isCaptain": false, "horizontalLayout": {"x": 0.371, "y": 0.89, "height": 0.195, "width": 0.741}, "verticalLayout": {"x": 0.11, "y": 0.371, "height": 0.2, "width": 0.195}, "performance": {"events": [], "substitutionEvents": [], "playerOfTheMatch": false}, "firstName": "Erdenis", "lastName": "Gurishta", "rankings": null}, {"id": 948468, "name": "Stivian Janku", "positionId": 33, "usualPlayingPositionId": 1, "shirtNumber": "18", "isCaptain": false, "horizontalLayout": {"x": 0.357, "y": 0.695, "height": 0.195, "width": 0.257}, "verticalLayout": {"x": 0.305, "y": 0.357, "height": 0.2, "width": 0.195}, "performance": {"events": [{"type": "yellowCard", "time": 36}], "substitutionEvents": [{"time": 46, "type": "subOut", "reason": "tactical"}], "playerOfTheMatch": false}, "firstName": "Stivian", "lastName": "Janku", "rankings": null}, {"id": 1067465, "name": "Rudolf Turkaj", "positionId": 35, "usualPlayingPositionId": 1, "shirtNumber": "17", "isCaptain": false, "horizontalLayout": {"x": 0.357, "y": 0.5, "height": 0.195, "width": 0.257}, "verticalLayout": {"x": 0.5, "y": 0.357, "height": 0.2, "width": 0.195}, "performance": {"events": [{"type": "yellowCard", "time": 60}], "substitutionEvents": [], "playerOfTheMatch": false}, "firstName": "Rudolf", "lastName": "Turkaj", "rankings": null}, {"id": 949386, "name": "Andi Hadroj", "positionId": 37, "usualPlayingPositionId": 1, "shirtNumber": "5", "isCaptain": false, "horizontalLayout": {"x": 0.357, "y": 0.305, "height": 0.195, "width": 0.257}, "verticalLayout": {"x": 0.695, "y": 0.357, "height": 0.2, "width": 0.195}, "performance": {"events": [], "substitutionEvents": [], "playerOfTheMatch": false}, "firstName": "Andi", "lastName": "Hadroj", "rankings": null}, {"id": 762023, "name": "Esin Hakaj", "positionId": 39, "usualPlayingPositionId": 2, "shirtNumber": "22", "isCaptain": false, "horizontalLayout": {"x": 0.371, "y": 0.11, "height": 0.195, "width": 0.243}, "verticalLayout": {"x": 0.89, "y": 0.371, "height": 0.2, "width": 0.195}, "performance": {"events": [], "substitutionEvents": [{"time": 64, "type": "subOut", "reason": "tactical"}], "playerOfTheMatch": false}, "firstName": "Esin", "lastName": "Hakaj", "rankings": null}, {"id": 949388, "name": "Serxho Ujka", "positionId": 73, "usualPlayingPositionId": 2, "shirtNumber": "21", "isCaptain": false, "horizontalLayout": {"x": 0.613, "y": 0.79, "height": 0.195, "width": 0.243}, "verticalLayout": {"x": 0.21, "y": 0.613, "height": 0.2, "width": 0.29}, "performance": {"events": [], "substitutionEvents": [], "playerOfTheMatch": false}, "firstName": "Serxho", "lastName": "Ujka", "rankings": null}, {"id": 1284548, "name": "Arinaldo Rrapaj", "positionId": 75, "usualPlayingPositionId": 2, "shirtNumber": "15", "isCaptain": false, "horizontalLayout": {"x": 0.613, "y": 0.5, "height": 0.195, "width": 0.257}, "verticalLayout": {"x": 0.5, "y": 0.613, "height": 0.2, "width": 0.29}, "performance": {"events": [], "substitutionEvents": [], "playerOfTheMatch": false}, "firstName": "Arinaldo", "lastName": "Rrapaj", "rankings": null}, {"id": 1067060, "name": "Sherif Kallaku", "positionId": 77, "usualPlayingPositionId": 2, "shirtNumber": "8", "isCaptain": false, "horizontalLayout": {"x": 0.613, "y": 0.21, "height": 0.195, "width": 0.257}, "verticalLayout": {"x": 0.79, "y": 0.613, "height": 0.2, "width": 0.29}, "performance": {"events": [], "substitutionEvents": [{"time": 46, "type": "subOut", "reason": "tactical"}], "playerOfTheMatch": false}, "firstName": "Sherif", "lastName": "Kallaku", "rankings": null}, {"id": 855297, "name": "Kristal Abazaj", "positionId": 104, "usualPlayingPositionId": 3, "shirtNumber": "7", "isCaptain": false, "horizontalLayout": {"x": 0.87, "y": 0.7, "height": 0.195, "width": 0.257}, "verticalLayout": {"x": 0.3, "y": 0.87, "height": 0.2, "width": 0.4}, "performance": {"events": [], "substitutionEvents": [{"time": 81, "type": "subOut", "reason": "tactical"}], "playerOfTheMatch": false}, "firstName": "Kristal", "lastName": "Abazaj", "rankings": null}, {"id": 1159654, "name": "Tedi Cara", "positionId": 106, "usualPlayingPositionId": 3, "shirtNumber": "20", "isCaptain": false, "horizontalLayout": {"x": 0.87, "y": 0.3, "height": 0.195, "width": 0.257}, "verticalLayout": {"x": 0.7, "y": 0.87, "height": 0.2, "width": 0.4}, "performance": {"events": [], "substitutionEvents": [{"time": 65, "type": "subOut", "reason": "tactical"}], "playerOfTheMatch": false}, "firstName": "Tedi", "lastName": "Cara", "rankings": null}], "subs": [{"id": 1178779, "name": "Alen Sherri", "positionId": 0, "usualPlayingPositionId": 0, "shirtNumber": "12", "isCaptain": false, "performance": {"events": [], "substitutionEvents": [{"time": 46, "type": "subIn", "reason": "tactical"}], "playerOfTheMatch": false}, "firstName": "Alen", "lastName": "Sherri", "rankings": null}, {"id": 948198, "name": "Eneo Bitri", "positionId": 0, "usualPlayingPositionId": 1, "shirtNumber": "3", "isCaptain": false, "performance": {"events": [{"type": "yellowCard", "time": 89}], "substitutionEvents": [{"time": 46, "type": "subIn", "reason": "tactical"}], "playerOfTheMatch": false}, "firstName": "Eneo", "lastName": "Bitri", "rankings": null}, {"id": 1173758, "name": "Herald Marku", "positionId": 0, "usualPlayingPositionId": 2, "shirtNumber": "13", "isCaptain": false, "performance": {"events": [], "substitutionEvents": [{"time": 46, "type": "subIn", "reason": "tactical"}], "playerOfTheMatch": false}, "firstName": "Herald", "lastName": "Marku", "rankings": null}, {"id": 1169358, "name": "Marsel Ismajlgeci", "positionId": 0, "usualPlayingPositionId": 2, "shirtNumber": "16", "isCaptain": false, "performance": {"events": [], "substitutionEvents": [{"time": 64, "type": "subIn", "reason": "tactical"}], "playerOfTheMatch": false}, "firstName": "Marsel", "lastName": "Ismajlgeci", "rankings": null}, {"id": 1306240, "name": "Xhuliano Skuka", "positionId": 0, "usualPlayingPositionId": 3, "shirtNumber": "10", "isCaptain": false, "performance": {"events": [], "substitutionEvents": [{"time": 65, "type": "subIn", "reason": "tactical"}], "playerOfTheMatch": false}, "firstName": "Xhuliano", "lastName": "Skuka", "rankings": null}, {"id": 948251, "name": "Redon Xhixha", "positionId": 0, "usualPlayingPositionId": 3, "shirtNumber": "11", "isCaptain": false, "performance": {"events": [], "substitutionEvents": [{"time": 81, "type": "subIn", "reason": "tactical"}], "playerOfTheMatch": false}, "firstName": "Redon", "lastName": "Xhixha", "rankings": null}, {"id": 1178778, "name": "Albion Marku", "positionId": 0, "usualPlayingPositionId": 1, "shirtNumber": "6", "isCaptain": false, "performance": {"events": [], "substitutionEvents": [], "playerOfTheMatch": false}, "firstName": "Albion", "lastName": "Marku", "rankings": null}, {"id": 762440, "name": "Arbin Zejnullai", "positionId": 0, "usualPlayingPositionId": 2, "shirtNumber": "19", "isCaptain": false, "performance": {"events": [], "substitutionEvents": [], "playerOfTheMatch": false}, "firstName": "Arbin", "lastName": "Zejnullai", "rankings": null}, {"id": 747062, "name": "Ardit Deliu", "positionId": 0, "usualPlayingPositionId": 2, "shirtNumber": "9", "isCaptain": false, "performance": {"events": [], "substitutionEvents": [], "playerOfTheMatch": false}, "firstName": "Ardit", "lastName": "Deliu", "rankings": null}, {"id": 1067464, "name": "Arlis Shala", "positionId": 0, "usualPlayingPositionId": 0, "shirtNumber": "23", "isCaptain": false, "performance": {"events": [], "substitutionEvents": [], "playerOfTheMatch": false}, "firstName": "Arlis", "lastName": "Shala", "rankings": null}, {"id": 1067052, "name": "Artan Jazxhi", "positionId": 0, "usualPlayingPositionId": 1, "shirtNumber": "4", "isCaptain": false, "performance": {"events": [], "substitutionEvents": [], "playerOfTheMatch": false}, "firstName": "Artan", "lastName": "Jazxhi", "rankings": null}, {"id": 1067062, "name": "Lorenco Vila", "positionId": 0, "usualPlayingPositionId": 3, "shirtNumber": "14", "isCaptain": false, "performance": {"events": [], "substitutionEvents": [], "playerOfTheMatch": false}, "firstName": "Lorenco", "lastName": "Vila", "rankings": null}], "unavailable": []}, "awayTeam": {"id": 5902, "name": "Qatar", "formation": "4-4-2", "starters": [{"id": 117496, "name": "Saad Al Sheeb", "positionId": 11, "usualPlayingPositionId": 0, "shirtNumber": "1", "isCaptain": false, "horizontalLayout": {"x": 0.1, "y": 0.5, "height": 0.25, "width": 0.2}, "verticalLayout": {"x": 0.5, "y": 0.1, "height": 0.2, "width": 1}, "performance": {"events": [], "substitutionEvents": [], "playerOfTheMatch": false}, "firstName": "Saad", "lastName": "Al Sheeb", "rankings": null}, {"id": 309153, "name": "Karim Boudiaf", "positionId": 32, "usualPlayingPositionId": 2, "shirtNumber": "12", "isCaptain": false, "horizontalLayout": {"x": 0.357, "y": 0.875, "height": 0.25, "width": 0.257}, "verticalLayout": {"x": 0.125, "y": 0.357, "height": 0.2, "width": 0.25}, "performance": {"events": [], "substitutionEvents": [{"time": 75, "type": "subOut", "reason": "tactical"}], "playerOfTheMatch": false}, "firstName": "Karim", "lastName": "Boudiaf", "rankings": null}, {"id": 734637, "name": "Pedro Miguel", "positionId": 34, "usualPlayingPositionId": 1, "shirtNumber": "2", "isCaptain": false, "horizontalLayout": {"x": 0.357, "y": 0.625, "height": 0.25, "width": 0.257}, "verticalLayout": {"x": 0.375, "y": 0.357, "height": 0.2, "width": 0.25}, "performance": {"events": [], "substitutionEvents": [{"time": 75, "type": "subOut", "reason": "tactical"}], "playerOfTheMatch": false}, "firstName": "Pedro", "lastName": "Miguel", "rankings": null}, {"id": 251923, "name": "Abdelkarim Hasan Fadlalla", "positionId": 36, "usualPlayingPositionId": 1, "shirtNumber": "3", "isCaptain": false, "horizontalLayout": {"x": 0.357, "y": 0.375, "height": 0.25, "width": 0.257}, "verticalLayout": {"x": 0.625, "y": 0.357, "height": 0.2, "width": 0.25}, "performance": {"events": [{"type": "yellowCard", "time": 64}], "substitutionEvents": [], "playerOfTheMatch": false}, "firstName": "Abdelkarim Hasan", "lastName": "Fadlalla", "rankings": null}, {"id": 308909, "name": "Abdulaziz Hatem", "positionId": 38, "usualPlayingPositionId": 2, "shirtNumber": "6", "isCaptain": false, "horizontalLayout": {"x": 0.357, "y": 0.125, "height": 0.25, "width": 0.257}, "verticalLayout": {"x": 0.875, "y": 0.357, "height": 0.2, "width": 0.25}, "performance": {"events": [], "substitutionEvents": [{"time": 61, "type": "subOut", "reason": "tactical"}], "playerOfTheMatch": false}, "firstName": "Abdulaziz", "lastName": "Hatem", "rankings": null}, {"id": 644017, "name": "Almoez Ali", "positionId": 72, "usualPlayingPositionId": 3, "shirtNumber": "19", "isCaptain": false, "horizontalLayout": {"x": 0.613, "y": 0.875, "height": 0.25, "width": 0.257}, "verticalLayout": {"x": 0.125, "y": 0.613, "height": 0.2, "width": 0.25}, "performance": {"events": [{"type": "goal", "time": 37}], "substitutionEvents": [{"time": 75, "type": "subOut", "reason": "tactical"}], "playerOfTheMatch": false}, "firstName": "Almoez", "lastName": "Ali", "rankings": null}, {"id": 644016, "name": "Bassam Al-Rawi", "positionId": 74, "usualPlayingPositionId": 1, "shirtNumber": "15", "isCaptain": false, "horizontalLayout": {"x": 0.613, "y": 0.625, "height": 0.25, "width": 0.257}, "verticalLayout": {"x": 0.375, "y": 0.613, "height": 0.2, "width": 0.25}, "performance": {"events": [], "substitutionEvents": [], "playerOfTheMatch": false}, "firstName": "Bassam", "lastName": "Al-Rawi", "rankings": null}, {"id": 644018, "name": "Tarek Salman", "positionId": 76, "usualPlayingPositionId": 1, "shirtNumber": "5", "isCaptain": false, "horizontalLayout": {"x": 0.613, "y": 0.375, "height": 0.25, "width": 0.257}, "verticalLayout": {"x": 0.625, "y": 0.613, "height": 0.2, "width": 0.25}, "performance": {"events": [], "substitutionEvents": [], "playerOfTheMatch": false}, "firstName": "Tarek", "lastName": "Salman", "rankings": null}, {"id": 937414, "name": "Homam Elamin", "positionId": 78, "usualPlayingPositionId": 1, "shirtNumber": "14", "isCaptain": false, "horizontalLayout": {"x": 0.613, "y": 0.125, "height": 0.25, "width": 0.257}, "verticalLayout": {"x": 0.875, "y": 0.613, "height": 0.2, "width": 0.25}, "performance": {"events": [], "substitutionEvents": [{"time": 61, "type": "subOut", "reason": "tactical"}], "playerOfTheMatch": false}, "firstName": "Homam", "lastName": "Elamin", "rankings": null}, {"id": 264096, "name": "Ahmed Alaaeldin", "positionId": 104, "usualPlayingPositionId": 3, "isCaptain": false, "horizontalLayout": {"x": 0.87, "y": 0.7, "height": 0.25, "width": 0.257}, "verticalLayout": {"x": 0.3, "y": 0.87, "height": 0.2, "width": 0.4}, "performance": {"events": [], "substitutionEvents": [{"time": 26, "type": "subOut", "reason": "tactical"}], "playerOfTheMatch": false}, "firstName": "Ahmed", "lastName": "Alaaeldin", "rankings": null}, {"id": 524005, "name": "Ali Assadalla", "positionId": 106, "usualPlayingPositionId": 2, "shirtNumber": "8", "isCaptain": false, "horizontalLayout": {"x": 0.87, "y": 0.3, "height": 0.25, "width": 0.257}, "verticalLayout": {"x": 0.7, "y": 0.87, "height": 0.2, "width": 0.4}, "performance": {"events": [], "substitutionEvents": [], "playerOfTheMatch": false}, "firstName": "Ali", "lastName": "Assadalla", "rankings": null}], "subs": [{"id": 431151, "name": "Mohammed Muntari", "positionId": 0, "usualPlayingPositionId": 3, "shirtNumber": "9", "isCaptain": false, "performance": {"events": [], "substitutionEvents": [{"time": 26, "type": "subIn", "reason": "tactical"}], "playerOfTheMatch": false}, "firstName": "Mohammed", "lastName": "Muntari", "rankings": null}, {"id": 1009249, "name": "Mohammed Waad", "positionId": 0, "usualPlayingPositionId": 2, "shirtNumber": "4", "isCaptain": false, "performance": {"events": [], "substitutionEvents": [{"time": 61, "type": "subIn", "reason": "tactical"}], "playerOfTheMatch": false}, "firstName": "Mohammed", "lastName": "Waad", "rankings": null}, {"id": 524007, "name": "Musab Kheder", "positionId": 0, "usualPlayingPositionId": 1, "shirtNumber": "13", "isCaptain": false, "performance": {"events": [], "substitutionEvents": [{"time": 61, "type": "subIn", "reason": "tactical"}], "playerOfTheMatch": false}, "firstName": "Musab", "lastName": "Kheder", "rankings": null}, {"id": 613792, "name": "Akram Afif", "positionId": 0, "usualPlayingPositionId": 3, "shirtNumber": "11", "isCaptain": false, "performance": {"events": [], "substitutionEvents": [{"time": 75, "type": "subIn", "reason": "tactical"}], "playerOfTheMatch": false}, "firstName": "Akram", "lastName": "Afif", "rankings": null}, {"id": 615414, "name": "Assim Madibo", "positionId": 0, "usualPlayingPositionId": 2, "shirtNumber": "23", "isCaptain": false, "performance": {"events": [], "substitutionEvents": [{"time": 75, "type": "subIn", "reason": "tactical"}], "playerOfTheMatch": false}, "firstName": "Assim", "lastName": "Madibo", "rankings": null}, {"id": 309173, "name": "Ismael Mohammad", "positionId": 0, "usualPlayingPositionId": 3, "shirtNumber": "17", "isCaptain": false, "performance": {"events": [{"type": "yellowCard", "time": 82}], "substitutionEvents": [{"time": 75, "type": "subIn", "reason": "tactical"}], "playerOfTheMatch": false}, "firstName": "Ismael", "lastName": "Mohammad", "rankings": null}, {"id": 831836, "name": "Abdelrahman Fahmi Moustafa", "positionId": 0, "usualPlayingPositionId": 3, "shirtNumber": "25", "isCaptain": false, "performance": {"events": [], "substitutionEvents": [], "playerOfTheMatch": false}, "firstName": "Abdelrahman Fahmi", "lastName": "Moustafa", "rankings": null}, {"id": 877646, "name": "Khalid Muneer Mazeed", "positionId": 0, "usualPlayingPositionId": 3, "shirtNumber": "18", "isCaptain": false, "performance": {"events": [], "substitutionEvents": [], "playerOfTheMatch": false}, "firstName": "Khalid Muneer", "lastName": "Mazeed", "rankings": null}, {"id": 922387, "name": "Meshaal Barsham", "positionId": 0, "usualPlayingPositionId": 0, "shirtNumber": "22", "isCaptain": false, "performance": {"events": [], "substitutionEvents": [], "playerOfTheMatch": false}, "firstName": "Meshaal", "lastName": "Barsham", "rankings": null}, {"id": 1233926, "name": "Naif Al Hadhrami", "positionId": 0, "usualPlayingPositionId": 2, "shirtNumber": "24", "isCaptain": false, "performance": {"events": [], "substitutionEvents": [], "playerOfTheMatch": false}, "firstName": "Naif", "lastName": "Al Hadhrami", "rankings": null}, {"id": 644008, "name": "Salem Al Hajri", "positionId": 0, "usualPlayingPositionId": 3, "isCaptain": false, "performance": {"events": [], "substitutionEvents": [], "playerOfTheMatch": false}, "firstName": "Salem", "lastName": "Al Hajri", "rankings": null}, {"id": 624137, "name": "Yousof Hassan Mohamed", "positionId": 0, "usualPlayingPositionId": 0, "shirtNumber": "21", "isCaptain": false, "performance": {"events": [], "substitutionEvents": [], "playerOfTheMatch": false}, "firstName": "Yousof Hassan", "lastName": "Mohamed", "rankings": null}], "unavailable": []}}, "table": false, "h2h": {"summary": [1, 0, 0], "matches": [{"time": {"utcTime": "2016-05-29T15:30:00.000Z"}, "matchUrl": "/matches/qatar-vs-albania/23ignv#2198748", "league": {"name": "Friendlies", "id": "114", "pageUrl": "/leagues/114/overview/friendlies"}, "home": {"name": "Albania", "id": "10024"}, "status": {"utcTime": "2016-05-29T15:30:00.000Z", "finished": true, "started": true, "cancelled": false, "awarded": false, "scoreStr": "3 - 1", "reason": {"short": "FT", "shortKey": "fulltime_short", "long": "Full-Time", "longKey": "finished"}}, "finished": false, "away": {"name": "Qatar", "id": "5902"}}]}, "momentum": false}, "seo": {"path": "albania-vs-qatar", "eventJSONLD": {"@context": "https://schema.org", "@type": "SportsEvent", "sport": "Football/Soccer", "homeTeam": {"@context": "https://schema.org", "@type": "SportsTeam", "name": "Albania", "sport": "Football/Soccer", "logo": "https://images.fotmob.com/image_resources/logo/teamlogo/10024.png", "url": "https://www.fotmob.com/teams/10024/overview/albania", "location": null, "memberOf": null}, "awayTeam": {"@context": "https://schema.org", "@type": "SportsTeam", "name": "Qatar", "sport": "Football/Soccer", "logo": "https://images.fotmob.com/image_resources/logo/teamlogo/5902.png", "url": "https://www.fotmob.com/teams/5902/overview/qatar", "location": null, "memberOf": null}, "name": "Albania vs Qatar", "description": "Follow Albania vs Qatar live on fotmob.com", "startDate": "2022-11-09T17:30:00.000Z", "endDate": "2022-11-09T19:30:00.000Z", "eventStatus": "https://schema.org/EventScheduled", "eventAttendanceMode": "https://schema.org/OnlineEventAttendanceMode", "location": {"@type": "Place", "name": "Unknown stadium name", "address": {"@type": "PostalAddress", "addressCountry": "Unknown country", "addressLocality": "Unknown city"}}, "image": ["https://images.fotmob.com/image_resources/logo/teamlogo/10024.png", "https://images.fotmob.com/image_resources/logo/teamlogo/5902.png"], "organizer": {"@type": "Organization", "name": "FotMob", "url": "https://www.fotmob.com", "logo": "https://www.fotmob.com/img/fotmob_icon_2017.png"}, "offers": {"@type": "Offer", "url": "https://www.fotmob.com/match/4058438", "availability": "https://schema.org/InStock", "price": "0", "priceCurrency": "USD", "validFrom": "2022-11-09T17:30:00.000Z"}, "performer": [{"@type": "SportsTeam", "name": "Albania", "url": "https://www.fotmob.com/teams/10024/overview/albania"}, {"@type": "SportsTeam", "name": "Qatar", "url": "https://www.fotmob.com/teams/5902/overview/qatar"}]}, "breadcrumbJSONLD": [{"@context": "https://schema.org", "@type": "BreadcrumbList", "itemListElement": [{"@type": "ListItem", "position": 1, "name": "Home", "item": "https://www.fotmob.com"}, {"@type": "ListItem", "position": 2, "name": "Friendlies", "item": "https://www.fotmob.com/leagues/114/overview/friendlies"}, {"@type": "ListItem", "position": 3, "name": "Albania - Qatar", "item": "https://www.fotmob.com/match/4058438"}]}, {"@context": "https://schema.org", "@type": "BreadcrumbList", "itemListElement": [{"@type": "ListItem", "position": 1, "name": "Home", "item": "https://www.fotmob.com"}, {"@type": "ListItem", "position": 2, "name": "Friendlies", "item": "https://www.fotmob.com/leagues/114/overview/friendlies"}, {"@type": "ListItem", "position": 3, "name": "Qatar", "item": "https://www.fotmob.com/teams/5902/overview/qatar"}, {"@type": "ListItem", "position": 4, "name": "Albania - Qatar", "item": "https://www.fotmob.com/match/4058438"}]}, {"@context": "https://schema.org", "@type": "BreadcrumbList", "itemListElement": [{"@type": "ListItem", "position": 1, "name": "Home", "item": "https://www.fotmob.com"}, {"@type": "ListItem", "position": 2, "name": "Friendlies", "item": "https://www.fotmob.com/leagues/114/overview/friendlies"}, {"@type": "ListItem", "position": 3, "name": "Albania", "item": "https://www.fotmob.com/teams/10024/overview/albania"}, {"@type": "ListItem", "position": 4, "name": "Albania - Qatar", "item": "https://www.fotmob.com/match/4058438"}]}], "faqJSONLD": {"@context": "https://schema.org", "@type": "FAQPage", "mainEntity": [{"@type": "Question", "name": "Who won between Albania and Qatar on Wed, 09 Nov 2022 17:30:00 GMT?", "acceptedAnswer": {"@type": "Answer", "text": "Qatar won 1\u20130 over Albania on Wed, 09 Nov 2022 17:30:00 GMT."}}]}}}